cordial/content_recommenders.py
cordial/setup.py
cordial-0.226.dist-info/LICENSE.txt
cordial-0.226.dist-info/METADATA
cordial-0.226.dist-info/WHEEL
cordial-0.226.dist-info/top_level.txt
cordial-0.226.dist-info/RECORD
