Metadata-Version: 2.1
Name: cordial
Version: 0.226
Summary: comprehensive recommender systems
Home-page: https://github.com/Vagif12/cordial
Author: Vagif Aliyev
Author-email: vagal2003@gmail.com
License: MIT
Keywords: machine learning,recommender systems,automation
Platform: UNKNOWN
Classifier: Development Status :: 3 - Alpha
Classifier: Intended Audience :: Developers
Classifier: Topic :: Software Development :: Build Tools
Classifier: License :: OSI Approved :: MIT License
Classifier: Programming Language :: Python :: 3
Classifier: Programming Language :: Python :: 3.4
Classifier: Programming Language :: Python :: 3.5
Classifier: Programming Language :: Python :: 3.6
Requires-Dist: pandas
Requires-Dist: numpy
Requires-Dist: networkx
Requires-Dist: scikit-learn
